README.txt
setup.py
docs/HISTORY.txt
docs/INSTALL.txt
docs/LICENSE.GPL
docs/LICENSE.txt
quintagroup/__init__.py
quintagroup.portlet.generichtml.egg-info/PKG-INFO
quintagroup.portlet.generichtml.egg-info/SOURCES.txt
quintagroup.portlet.generichtml.egg-info/dependency_links.txt
quintagroup.portlet.generichtml.egg-info/entry_points.txt
quintagroup.portlet.generichtml.egg-info/namespace_packages.txt
quintagroup.portlet.generichtml.egg-info/not-zip-safe
quintagroup.portlet.generichtml.egg-info/requires.txt
quintagroup.portlet.generichtml.egg-info/top_level.txt
quintagroup/portlet/__init__.py
quintagroup/portlet/generichtml/__init__.py
quintagroup/portlet/generichtml/configure.zcml
quintagroup/portlet/generichtml/generichtmlportlet.pt
quintagroup/portlet/generichtml/generichtmlportlet.py
quintagroup/portlet/generichtml/version.txt
quintagroup/portlet/generichtml/locales/quintagroup.portlet.generichtml.pot
quintagroup/portlet/generichtml/profiles/default/metadata.xml
quintagroup/portlet/generichtml/profiles/default/portlets.xml
quintagroup/portlet/generichtml/tests/__init__.py
quintagroup/portlet/generichtml/tests/base.py
quintagroup/portlet/generichtml/tests/test_portlet.py