Metadata-Version: 1.0
Name: quintagroup.portlet.generichtml
Version: 0.1
Summary: Static portlet without HTML filtering
Home-page: http://svn.quintagroup.com/products/quintagroup.portlet.generichtml
Author: Quintagroup
Author-email: support@quintagroup.com
License: GPL
Keywords: plone portlet static
Platform: UNKNOWN
Classifier: Framework :: Plone
Classifier: Programming Language :: Python
Classifier: Topic :: Software Development :: Libraries :: Python Modules
